{
  "manifest": {
    "publishingInformation": {
      "locales": {
        "en-US": {
          "summary": "It\u0027s a school activity",
          "examplePhrases": [
            "Alexa, open hello world",
            "say hello world",
            "help"
          ],
          "keywords": [
            "hello",
            "world",
            "help"
          ],
          "name": "Activity language",
          "description": "is a school practice about language change",
          "smallIconUri": "file://assets/images/en-US_smallIconUri.png",
          "updatesDescription": "It\u0027s a school activity",
          "largeIconUri": "file://assets/images/en-US_largeIconUri.png"
        },
        "es-MX": {
          "summary": "Es una actividad escolar",
          "examplePhrases": [
            "Alexa abre hola mundo",
            "hola",
            "ayuda"
          ],
          "keywords": [
            "hola",
            "mundo"
          ],
          "name": "Actividad Idioma",
          "description": "Es una actividad escolar sobre el cambio de idioma",
          "smallIconUri": "file://assets/images/es-MX_smallIconUri.png",
          "updatesDescription": "Es una actividad escolar",
          "largeIconUri": "file://assets/images/es-MX_largeIconUri.png"
        }
      },
      "automaticDistribution": {
        "isActive": false
      },
      "isAvailableWorldwide": false,
      "testingInstructions": "{\"ask_dist_username\":\"\",\"ask_dist_password\":\"\",\"ask_dist_testing_instructions\":\"Esta skill es solo una prueba escolar\"}",
      "category": "EDUCATION_AND_REFERENCE",
      "distributionMode": "PUBLIC",
      "distributionCountries": [
        "MX"
      ]
    },
    "apis": {
      "custom": {
        "endpoint": {
          "uri": "arn:aws:lambda:us-east-1:046533039791:function:994fa535-0b8e-4885-896d-692b32f39c13:Release_0"
        },
        "interfaces": [],
        "locales": {},
        "regions": {
          "EU": {
            "endpoint": {
              "uri": "arn:aws:lambda:eu-west-1:046533039791:function:994fa535-0b8e-4885-896d-692b32f39c13:Release_0"
            }
          },
          "NA": {
            "endpoint": {
              "uri": "arn:aws:lambda:us-east-1:046533039791:function:994fa535-0b8e-4885-896d-692b32f39c13:Release_0"
            }
          },
          "FE": {
            "endpoint": {
              "uri": "arn:aws:lambda:us-west-2:046533039791:function:994fa535-0b8e-4885-896d-692b32f39c13:Release_0"
            }
          }
        }
      }
    },
    "manifestVersion": "1.0",
    "privacyAndCompliance": {
      "allowsPurchases": false,
      "locales": {
        "en-US": {},
        "es-MX": {}
      },
      "containsAds": false,
      "isExportCompliant": true,
      "isChildDirected": false,
      "shoppingKit": {
        "isShoppingActionsEnabled": false,
        "isAmazonAssociatesOnAlexaEnabled": false
      },
      "usesPersonalInfo": false
    }
  }
}